{
	"info": {
		"_postman_id": "a8c1b2d3-e4f5-4a6b-8c9d-0e1f2a3b4c5d",
		"name": "Splitwiser API",
		"schema": "https://schema.getpostman.com/json/collection/v2.1.0/collection.json",
		"description": "A complete Postman collection for the Splitwiser API."
	},
	"item": [
		{
			"name": "Authentication",
			"item": [
				{
					"name": "Sign up with Email",
					"request": {
						"method": "POST",
						"header": [],
						"body": {
							"mode": "raw",
							"raw": "{\n  \"email\": \"testuser@example.com\",\n  \"password\": \"strongpassword123\",\n  \"name\": \"Test User\"\n}",
							"options": {
								"raw": {
									"language": "json"
								}
							}
						},
						"url": {
							"raw": "{{baseUrl}}/auth/signup/email",
							"host": [
								"{{baseUrl}}"
							],
							"path": [
								"auth",
								"signup",
								"email"
							]
						}
					},
					"response": []
				},
				{
					"name": "Login with Email",
					"request": {
						"method": "POST",
						"header": [],
						"body": {
							"mode": "raw",
							"raw": "{\n  \"email\": \"testuser@example.com\",\n  \"password\": \"strongpassword123\"\n}",
							"options": {
								"raw": {
									"language": "json"
								}
							}
						},
						"url": {
							"raw": "{{baseUrl}}/auth/login/email",
							"host": [
								"{{baseUrl}}"
							],
							"path": [
								"auth",
								"login",
								"email"
							]
						}
					},
					"response": []
				},
				{
					"name": "Refresh Token",
					"request": {
						"method": "POST",
						"header": [],
						"body": {
							"mode": "raw",
							"raw": "{\n  \"refresh_token\": \"your_refresh_token_here\"\n}",
							"options": {
								"raw": {
									"language": "json"
								}
							}
						},
						"url": {
							"raw": "{{baseUrl}}/auth/refresh",
							"host": [
								"{{baseUrl}}"
							],
							"path": [
								"auth",
								"refresh"
							]
						}
					},
					"response": []
				},
				{
					"name": "Verify Token",
					"request": {
						"method": "POST",
						"header": [],
						"body": {
							"mode": "raw",
							"raw": "{\n  \"access_token\": \"{{accessToken}}\"\n}",
							"options": {
								"raw": {
									"language": "json"
								}
							}
						},
						"url": {
							"raw": "{{baseUrl}}/auth/token/verify",
							"host": [
								"{{baseUrl}}"
							],
							"path": [
								"auth",
								"token",
								"verify"
							]
						}
					},
					"response": []
				}
			]
		},
		{
			"name": "User Profile",
			"item": [
				{
					"name": "Get Current User Profile",
					"request": {
						"method": "GET",
						"header": [],
						"url": {
							"raw": "{{baseUrl}}/users/me",
							"host": [
								"{{baseUrl}}"
							],
							"path": [
								"users",
								"me"
							]
						}
					},
					"response": []
				},
				{
					"name": "Update User Profile",
					"request": {
						"method": "PATCH",
						"header": [],
						"body": {
							"mode": "raw",
							"raw": "{\n  \"name\": \"Updated Name\",\n  \"currency\": \"EUR\"\n}",
							"options": {
								"raw": {
									"language": "json"
								}
							}
						},
						"url": {
							"raw": "{{baseUrl}}/users/me",
							"host": [
								"{{baseUrl}}"
							],
							"path": [
								"users",
								"me"
							]
						}
					},
					"response": []
				},
				{
					"name": "Delete User Account",
					"request": {
						"method": "DELETE",
						"header": [],
						"url": {
							"raw": "{{baseUrl}}/users/me",
							"host": [
								"{{baseUrl}}"
							],
							"path": [
								"users",
								"me"
							]
						}
					},
					"response": []
				}
			]
		},
		{
			"name": "Groups",
			"item": [
				{
					"name": "Create Group",
					"request": {
						"method": "POST",
						"header": [],
						"body": {
							"mode": "raw",
							"raw": "{\n  \"name\": \"My New Group\",\n  \"currency\": \"USD\"\n}",
							"options": {
								"raw": {
									"language": "json"
								}
							}
						},
						"url": {
							"raw": "{{baseUrl}}/groups",
							"host": [
								"{{baseUrl}}"
							],
							"path": [
								"groups"
							]
						}
					},
					"response": []
				},
				{
					"name": "List User's Groups",
					"request": {
						"method": "GET",
						"header": [],
						"url": {
							"raw": "{{baseUrl}}/groups",
							"host": [
								"{{baseUrl}}"
							],
							"path": [
								"groups"
							]
						}
					},
					"response": []
				},
				{
					"name": "Join Group",
					"request": {
						"method": "POST",
						"header": [],
						"body": {
							"mode": "raw",
							"raw": "{\n  \"joinCode\": \"A1B2C3\"\n}",
							"options": {
								"raw": {
									"language": "json"
								}
							}
						},
						"url": {
							"raw": "{{baseUrl}}/groups/join",
							"host": [
								"{{baseUrl}}"
							],
							"path": [
								"groups",
								"join"
							]
						}
					},
					"response": []
				},
				{
					"name": "Get Group Details",
					"request": {
						"method": "GET",
						"header": [],
						"url": {
							"raw": "{{baseUrl}}/groups/{{groupId}}",
							"host": [
								"{{baseUrl}}"
							],
							"path": [
								"groups",
								"{{groupId}}"
							]
						}
					},
					"response": []
				}
			]
		},
		{
			"name": "Expenses",
			"item": [
				{
					"name": "Create Expense",
					"request": {
						"method": "POST",
						"header": [],
						"body": {
							"mode": "raw",
							"raw": "{\n  \"description\": \"Dinner\",\n  \"amount\": 120.00,\n  \"paidBy\": \"{{userId}}\",\n  \"splitType\": \"equal\",\n  \"splits\": [\n    {\"userId\": \"{{userId}}\", \"amount\": 60.00},\n    {\"userId\": \"{{friendId}}\", \"amount\": 60.00}\n  ]\n}",
							"options": {
								"raw": {
									"language": "json"
								}
							}
						},
						"url": {
							"raw": "{{baseUrl}}/groups/{{groupId}}/expenses",
							"host": [
								"{{baseUrl}}"
							],
							"path": [
								"groups",
								"{{groupId}}",
								"expenses"
							]
						}
					},
					"response": []
				},
				{
					"name": "List Group Expenses",
					"request": {
						"method": "GET",
						"header": [],
						"url": {
							"raw": "{{baseUrl}}/groups/{{groupId}}/expenses",
							"host": [
								"{{baseUrl}}"
							],
							"path": [
								"groups",
								"{{groupId}}",
								"expenses"
							]
						}
					},
					"response": []
				}
			]
		},
		{
			"name": "Settlements",
			"item": [
				{
					"name": "Manually Record Payment",
					"request": {
						"method": "POST",
						"header": [],
						"body": {
							"mode": "raw",
							"raw": "{\n  \"payer_id\": \"{{userId}}\",\n  \"payee_id\": \"{{friendId}}\",\n  \"amount\": 50.00\n}",
							"options": {
								"raw": {
									"language": "json"
								}
							}
						},
						"url": {
							"raw": "{{baseUrl}}/groups/{{groupId}}/settlements",
							"host": [
								"{{baseUrl}}"
							],
							"path": [
								"groups",
								"{{groupId}}",
								"settlements"
							]
						}
					},
					"response": []
				},
				{
					"name": "Optimize Settlements",
					"request": {
						"method": "POST",
						"header": [],
						"url": {
							"raw": "{{baseUrl}}/groups/{{groupId}}/settlements/optimize",
							"host": [
								"{{baseUrl}}"
							],
							"path": [
								"groups",
								"{{groupId}}",
								"settlements",
								"optimize"
							]
						}
					},
					"response": []
				}
			]
		}
	],
	"auth": {
		"type": "bearer",
		"bearer": [
			{
				"key": "token",
				"value": "{{accessToken}}",
				"type": "string"
			}
		]
	},
	"variable": [
		{
			"key": "baseUrl",
			"value": "http://localhost:8000"
		},
		{
			"key": "accessToken",
			"value": ""
		},
		{
			"key": "groupId",
			"value": ""
		},
		{
			"key": "userId",
			"value": ""
		},
		{
			"key": "friendId",
			"value": ""
		}
	]
}
